LICENSE.txt
README.md
setup.cfg
setup.py
lotus_client/__init__.py
lotus_client/api_client.py
lotus_client/configuration.py
lotus_client/rest.py
lotus_client.egg-info/PKG-INFO
lotus_client.egg-info/SOURCES.txt
lotus_client.egg-info/dependency_links.txt
lotus_client.egg-info/requires.txt
lotus_client.egg-info/top_level.txt
lotus_client/api/__init__.py
lotus_client/api/api_api.py
lotus_client/api/app_api.py
lotus_client/api/stripe_api.py
lotus_client/models/__init__.py
lotus_client/models/access_methods_subscription_record.py
lotus_client/models/action.py
lotus_client/models/add_feature_request.py
lotus_client/models/add_feature_response.py
lotus_client/models/add_feature_to_add_on_request.py
lotus_client/models/add_feature_to_add_on_response.py
lotus_client/models/add_feature_to_plan_request.py
lotus_client/models/add_feature_to_plan_response.py
lotus_client/models/add_feature_to_plan_version_number_response.py
lotus_client/models/add_on_create_request.py
lotus_client/models/add_on_detail.py
lotus_client/models/add_on_subscription_record.py
lotus_client/models/add_on_subscription_record_create_request.py
lotus_client/models/add_on_update.py
lotus_client/models/add_on_version.py
lotus_client/models/add_on_version_create_request.py
lotus_client/models/add_on_version_detail.py
lotus_client/models/add_on_version_update.py
lotus_client/models/add_plan_tags.py
lotus_client/models/add_plan_tags_request.py
lotus_client/models/add_target_customer_response.py
lotus_client/models/address.py
lotus_client/models/address_request.py
lotus_client/models/all_of_add_on_create_request_initial_version.py
lotus_client/models/all_of_add_on_version_currency.py
lotus_client/models/all_of_add_on_version_detail_currency.py
lotus_client/models/all_of_analysis_detail_analysis_results.py
lotus_client/models/all_of_customer_address.py
lotus_client/models/all_of_customer_balance_adjustment_amount_paid_currency.py
lotus_client/models/all_of_customer_billing_address.py
lotus_client/models/all_of_customer_create_request_address.py
lotus_client/models/all_of_customer_create_request_billing_address.py
lotus_client/models/all_of_customer_create_request_shipping_address.py
