Metadata-Version: 1.2
Name: lotus-client
Version: 1.0.2
Summary: Lotus API
Home-page: UNKNOWN
Author: do_trieu_hai
Author-email: dotrieuhai2k@gmail.com
License: UNKNOWN
Keywords: Swagger,Lotus API
Platform: UNKNOWN
Classifier: Programming Language :: Python :: 3
Classifier: License :: OSI Approved :: MIT License
Classifier: Operating System :: OS Independent
Requires-Python: >=3.6
